pylint_silent/__init__.py
pylint_silent/__main__.py
pylint_silent-1.4.2.dist-info/licenses/LICENSE
pylint_silent-1.4.2.dist-info/METADATA
pylint_silent-1.4.2.dist-info/WHEEL
pylint_silent-1.4.2.dist-info/entry_points.txt
pylint_silent-1.4.2.dist-info/top_level.txt
pylint_silent-1.4.2.dist-info/RECORD
