Metadata-Version: 2.4
Name: pylint-silent
Version: 1.4.2
Summary: Automatically add code comments to silence the output of pylint
Author-email: Udi Fuchs <udifuchs@gmail.com>
License-Expression: GPL-2.0-or-later
Project-URL: Homepage, http://github.com/udifuchs/pylint-silent
Keywords: pylint
Classifier: Topic :: Software Development :: Quality Assurance
Classifier: Development Status :: 5 - Production/Stable
Classifier: Environment :: Console
Classifier: Programming Language :: Python
Classifier: Programming Language :: Python :: 3
Classifier: Programming Language :: Python :: 3 :: Only
Classifier: Programming Language :: Python :: 3.9
Classifier: Programming Language :: Python :: 3.10
Classifier: Programming Language :: Python :: 3.11
Classifier: Programming Language :: Python :: 3.12
Classifier: Programming Language :: Python :: 3.13
Classifier: Programming Language :: Python :: 3.14
Classifier: Operating System :: OS Independent
Classifier: Intended Audience :: Developers
Requires-Python: >=3.9
License-File: LICENSE
Dynamic: license-file
